README.md
setup.cfg
setup.py
pyroaman/__init__.py
pyroaman/block.py
pyroaman/database.py
pyroaman/main.py
pyroaman/parsing.py
pyroaman.egg-info/PKG-INFO
pyroaman.egg-info/SOURCES.txt
pyroaman.egg-info/dependency_links.txt
pyroaman.egg-info/requires.txt
pyroaman.egg-info/top_level.txt