Metadata-Version: 2.1
Name: pyroaman
Version: 0.1.1
Summary: Roam Research with Python
Home-page: https://github.com/br-g/pyroaman
Author: Bruno Godefroy
Author-email: brgo@mail.com
License: MIT
Download-URL: https://github.com/br-g/pyroaman/archive/v0.1.1.tar.gz
Keywords: Roam Research
Platform: UNKNOWN
Classifier: Development Status :: 5 - Production/Stable
Classifier: Intended Audience :: Developers
Classifier: Topic :: Software Development :: Libraries :: Python Modules
Classifier: License :: OSI Approved :: MIT License
Classifier: Programming Language :: Python :: 3.6
Requires-Python: >=3.6
